yunfan/__init__.py
yunfan/downloader.py
yunfan-0.0.6.dist-info/METADATA
yunfan-0.0.6.dist-info/WHEEL
yunfan-0.0.6.dist-info/top_level.txt
yunfan-0.0.6.dist-info/RECORD
