Metadata-Version: 2.1
Name: yunfan
Version: 0.0.6
Summary: Yunfan platform interface toolkit.
Home-page: UNKNOWN
Author: Wei Zhang
Author-email: <zhangw355@foxmail.com>
License: UNKNOWN
Keywords: python,yunfan
Platform: UNKNOWN
Classifier: Development Status :: 3 - Alpha
Classifier: Intended Audience :: Developers
Classifier: Programming Language :: Python :: 3
Classifier: Operating System :: Microsoft :: Windows
Classifier: Operating System :: POSIX :: Linux
